st_deta_connection/__init__.py
st_deta_connection/connections.py
st_deta_connection-0.0.3.dist-info/LICENSE.txt
st_deta_connection-0.0.3.dist-info/METADATA
st_deta_connection-0.0.3.dist-info/WHEEL
st_deta_connection-0.0.3.dist-info/top_level.txt
st_deta_connection-0.0.3.dist-info/RECORD
