Metadata-Version: 2.1
Name: st-deta-connection
Version: 0.0.3
Summary: A Streamlit component to connect to Deta Base and insert and fetch data from it.
Home-page: https://github.com/mohitrajsinha/st_deta_connection
Author: Mohit Raj Sinha
Author-email: mhtrajsinha@gmail.com
License: MIT
Classifier: License :: OSI Approved :: MIT License
Classifier: Programming Language :: Python :: 3.10
Classifier: Operating System :: OS Independent
License-File: LICENSE.txt
Requires-Dist: deta >=1.2.0
Requires-Dist: streamlit >=1.29.0
Requires-Dist: streamlit-option-menu >=0.3.6
